LICENSE
MANIFEST.in
README.rst
setup.py
spec.yaml
docs/Makefile
docs/conf.py
docs/index.rst
modulemd/__init__.py
modulemd/api.py
modulemd/artifacts.py
modulemd/filter.py
modulemd/profile.py
modulemd.egg-info/PKG-INFO
modulemd.egg-info/SOURCES.txt
modulemd.egg-info/dependency_links.txt
modulemd.egg-info/requires.txt
modulemd.egg-info/top_level.txt
modulemd/buildopts/__init__.py
modulemd/buildopts/base.py
modulemd/buildopts/rpms.py
modulemd/components/__init__.py
modulemd/components/base.py
modulemd/components/module.py
modulemd/components/rpm.py
modulemd/tests/__init__.py
modulemd/tests/test_basic.py
modulemd/tests/test_convenience.py
modulemd/tests/test_io.py
modulemd/tests/test_validation.py