Metadata-Version: 1.1
Name: modulemd
Version: 1.3.3
Summary: A python library for manipulation of the proposed module metadata format.
Home-page: https://pagure.io/modulemd
Author: Petr Šabata
Author-email: contyk@redhat.com
License: MIT
Keywords: modularization modularity module metadata
Platform: UNKNOWN
Classifier: Development Status :: 5 - Production/Stable
Classifier: Topic :: Software Development :: Libraries
Classifier: License :: OSI Approved :: MIT License
